movescount_sync.py
movescount_sync-1.0.dist-info/DESCRIPTION.rst
movescount_sync-1.0.dist-info/METADATA
movescount_sync-1.0.dist-info/RECORD
movescount_sync-1.0.dist-info/WHEEL
movescount_sync-1.0.dist-info/entry_points.txt
movescount_sync-1.0.dist-info/metadata.json
movescount_sync-1.0.dist-info/top_level.txt
