Metadata-Version: 2.0
Name: movescount-sync
Version: 1.0
Summary: Fetch moves from movescount.com
Home-page: https://github.com/brutasse/movescount-sync
Author: Bruno Renié
Author-email: UNKNOWN
License: BSD
Platform: any
Classifier: License :: OSI Approved :: BSD License
Classifier: Operating System :: OS Independent
Classifier: Programming Language :: Python :: 3
Requires-Dist: requests
